{
    "levels":[
        {
            "name": "level52",
            "title": "No permits, no parley",
            "sectorCount": 2,
            "levelHash": "44FB559E",
            "sector1Hash": "F4A7A9A5",
            "sector2Hash": "3C06861D",
            "sector1Hashes": [
                "1CB5B52D",
                "EB3CB077",
                "D65C99C7",
                "91FCE317",
                "AC9CCAA7",
                "1EBC16B7",
                "23DC3F07",
                "647C45D7",
                "591C6C67",
                "5B15CFFD",
                "6675E64D",
                "D4553A5D",
                "E93513ED",
                "AE95693D",
                "93F5408D",
                "11A5D75C",
                "2CC5FEEC"
            ],
            "sector2Hashes": [
                "D4149A95",
                "2E4E2AE6",
                "132E0356",
                "548E7986",
                "69EE5036",
                "DBCE8C26",
                "E6AEA596",
                "A10EDF46",
                "9C6EF6F6",
                "1E3E6127",
                "235E4897",
                "93B4E045",
                "A8DA5848",
                "95BA71F8",
                "D21A0B28",
                "EF7A2298",
                "5D5AFE88",
                "603AD738",
                "279AADE8",
                "AED4C9F5",
                "1CF415E5",
                "21943C55",
                "66344685",
                "5B546F35",
                "D904F8E4",
                "E464D154"
            ]
        },
        {
            "name": "level80",
            "title": "Real live bunch",
            "sectorCount": 2,
            "levelHash": "82A51520",
            "sector1Hash": "3BC6349F",
            "sector2Hash": "F3671B27",
            "sector1Hashes": [
                "D3D42817",
                "2DFF0858",
                "109F21E8",
                "573F5B38",
                "947452C7",
                "A9147B77",
                "1B34A767",
                "26548ED7",
                "61F4F407",
                "5C94DDB7",
                "DEC44A66",
                "E3A463D6"
            ],
            "sector2Hashes": [
                "1B7507AF",
                "E88D92C9",
                "D5EDBB79",
                "924DC1A9",
                "AF2DE819",
                "1D0D3409",
                "206D1DB9",
                "67CD6769",
                "5AAD4ED9",
                "D8FDD908",
                "E59DF0B8",
                "5CD57D7F",
                "6E19E067",
                "14D9B307",
                "29B99AB7",
                "61B554CF",
                "D39588DF",
                "EEF5A16F",
                "A955DBBF",
                "9435F20F",
                "166565DE",
                "2B054C6E"
            ]
        },
        {
            "name": "level84",
            "title": "Come out to play",
            "sectorCount": 2,
            "levelHash": "7725B3E0",
            "sector1Hash": "322D94E5",
            "sector2Hash": "FA8CBB5D",
            "sector1Hashes": [
                "DA3F886D",
                "9D267BDA",
                "A046526A",
                "E7E628BA",
                "DA86010A",
                "68A6DD1A",
                "55C6F4AA",
                "12668E7A",
                "2F06A7CA",
                "AD56301B",
                "903619AB",
                "9D9FF2BD",
                "1BB20974",
                "26D220C4",
                "A0FFDB0D",
                "12DF071D",
                "2FBF2EAD",
                "681F547D",
                "557F7DCD",
                "D72FEA1C",
                "EA4FC3AC"
            ],
            "sector2Hashes": [
                "129EA7D5",
                "5854E14B",
                "6534C8FB",
                "2294B22B",
                "1FF49B9B",
                "ADD4478B",
                "90B46E3B",
                "D71414EB",
                "EA743D5B",
                "6824AA8A",
                "5544833A",
                "553EDD05",
                "DEC093E5",
                "E3A0BA55",
                "A400C085",
                "9960E935",
                "2B403525",
                "16201C95",
                "51806645",
                "6CE04FF5",
                "EEB0D824",
                "D3D0F194",
                "685EF4B5",
                "159C4040",
                "28FC69F0",
                "6F5C1320",
                "523C3A90",
                "E01CE680",
                "DD7CCF30",
                "9ADCB5E0",
                "A7BC9C50",
                "25EC0B81",
                "188C2231",
                "DA7E28A5",
                "089970F8",
                "35F95948",
                "72592398",
                "4F390A28",
                "FD19D638",
                "C079FF88",
                "87D98558",
                "BAB9ACE8",
                "38E93B39",
                "05891289",
                "E71E0115",
                "C3C5A35D",
                "A0BE7BC5",
                "9DDE5275",
                "1F8EC5A4",
                "22EEEC14"
            ]
        },
        {
            "name": "level107",
            "title": "Courtyard",
            "sectorCount": 2,
            "levelHash": "F7C3E4D2",
            "sector1Hash": "29FA7C41",
            "sector2Hash": "E15B53F9",
            "sector1Hashes": [
                "C1E860C9"
            ],
            "sector2Hashes": [
                "09494F71",
                "4EE935A1",
                "73891C11",
                "C1A9C001",
                "FCC9E9B1"
            ]
        }
    ]
}